{
  "movies": [
    {
      "id": 1,
      "title": "Mononoke Hime",
      "country": "Japão",
      "year": "1997",
      "poster": "https://upload.wikimedia.org/wikipedia/pt/e/ec/Mononoke_Hime_p%C3%B4ster.png"
    },
    {
      "id": 2,
      "title": "Parasita",
      "country": "Coreia do Sul",
      "year": "2019",
      "poster": "https://encrypted-tbn2.gstatic.com/images?q=tbn:ANd9GcQJmbajoepvv5M8KO0eev1s80qkpthWlbLvWR1L0BsMat307ypG"
    },
    {
      "id": 3,
      "title": "Tudo em Todo Lugar ao Mesmo Tempo",
      "country": "EUA",
      "year": "2022",
      "poster": "https://encrypted-tbn2.gstatic.com/images?q=tbn:ANd9GcRUIm9P_8LVR6KHcFvTvYvxjshn9I3oGdwZWqK7Svtx6InZHtje"
    },
    {
      "id": 4,
      "title": "Onde Está Segunda?",
      "country": "EUA",
      "year": "2017",
      "poster": "https://encrypted-tbn2.gstatic.com/images?q=tbn:ANd9GcRQSYAkQqamFhgtCJFWqjSV5q6ieVcaFGxnnbEW7JRh0eucc-GH"
    },
    {
      "id": 5,
      "title": "O Jogo da Imitação",
      "country": "EUA",
      "year": "2014",
      "poster": "https://encrypted-tbn0.gstatic.com/images?q=tbn:ANd9GcSbMYoam7K_x0CYtz0ljs47g_wtn2cXzUGPjmOGM5JNT4bzRWAt"
    },
    {
      "id": 6,
      "title": "Forrest Gump - O Contador de Histórias",
      "country": "EUA",
      "year": "1994",
      "poster": "https://encrypted-tbn2.gstatic.com/images?q=tbn:ANd9GcTFEXK7nOeOlpnsn9IxrdUc1Z53qnHLkE7kPAkhyCTf0mwJ8beF"
    },
    {
      "id": 7,
      "title": "Histórias Cruzadas",
      "country": "EUA",
      "year": "2011",
      "poster": "https://encrypted-tbn1.gstatic.com/images?q=tbn:ANd9GcR6huvT79HOwzOkQsLvwDQWuMtWvhPvJ33qyJVSwu3Ec-HdwsLx"
    },
    {
      "id": 8,
      "title": "Matrix",
      "country": "EUA",
      "year": "1999",
      "poster": "https://encrypted-tbn2.gstatic.com/images?q=tbn:ANd9GcQwLB63Bm8WaqqWPmYLi9_wEXXt47qq1UZBSzw05b9NrXlQyN-O"
    }
  ]
}
